Workbook

Sheet README
B2: Equity Research & Valuation of Asian Paints Ltd.
B4: Project period: January 2026 – February 2026
B6: OBJECTIVE
B7: Determine the intrinsic value of Asian Paints Ltd (NSE: ASIANPAINT) using a Discounted Cash Flow (DCF)
B8: model and a Comparable Company Analysis, and assess whether the stock is fairly valued relative to its
B9: January 2026 market price.
B11: HOW TO USE THIS WORKBOOK
B12: 1. Historical Financials - 5-year (FY2021-FY2025) actuals sourced from company filings, as compiled by Screener.in.
B13: 2. Assumptions - All forecast drivers (growth, margins, WACC, terminal growth). Blue text = editable input.
B14: 3. 3-Statement Forecast - FY2026E-FY2030E income statement, simplified balance sheet and cash flow, driven by Assumptions.
B15: 4. DCF Valuation - Free cash flow to firm, discounted at WACC, plus Gordon Growth terminal value.
B16: 5. Sensitivity Analysis - Value per share across a WACC x Terminal Growth grid.
... B37: than primary company filings line-by-line, so minor reclassification differences vs. the audited financial statements are possible.

Sheet Historicals
A1: Asian Paints Ltd - Historical Financials (Consolidated, Rs. Crore)
A2: Source: Screener.in, compiled from company annual reports / BSE filings
A4: Rs. Crore | B4: FY2021 | C4: FY2022 | D4: FY2023 | E4: FY2024 | F4: FY2025
A5: Net Sales | B5: 21713 | C5: 29101 | D5: 34489 | E5: 35495 | F5: 33906
A6: Total Expenses | B6: 16857 | C6: 24298 | D6: 28229 | E6: 27910 | F6: 27899
A7: EBITDA (Operating Profit) | B7: =B5-B6 -> 4856 | C7: =C5-C6 -> 4803 | D7: =D5-D6 -> 6260 | E7: =E5-E6 -> 7585 | F7: =F5-F6 -> 6007
A8: EBITDA Margin % | B8: =B7/B5 -> 0.22364482 | C8: =C7/C5 -> 0.16504587 | D8: =D7/D5 -> 0.18150715 | E8: =E7/E5 -> 0.21369207 | F8: =F7/F5 -> 0.17716628
A9: Other Income | B9: 332 | C9: 296 | D9: 431 | E9: 821 | F9: 350
A10: Interest Expense | B10: 92 | C10: 95 | D10: 144 | E10: 205 | F10: 227
A11: Depreciation & Amortization | B11: 791 | C11: 816 | D11: 858 | E11: 853 | F11: 1026
A12: Profit Before Tax | B12: =B7+B9-B10-B11 -> 4305 | C12: =C7+C9-C10-C11 -> 4188 | D12: =D7+D9-D10-D11 -> 5689 | E12: =E7+E9-E10-E11 -> 7348 | F12: =F7+F9-F10-F11 -> 5104
A13: Tax Rate % | B13: 0.26 | C13: 0.26 | D13: 0.26 | E13: 0.24 | F13: 0.27
A14: Net Profit (PAT) | B14: =B12*(1-B13) -> 3185.7 | C14: =C12*(1-C13) -> 3099.12 | D14: =D12*(1-D13) -> 4209.86 | E14: =E12*(1-E13) -> 5584.48 | F14: =F12*(1-F13) -> 3725.92
A15: Reported EPS (Rs.) | B15: 32.73 | C15: 31.59 | D15: 42.81 | E15: 56.92 | F15: 38.23
A17: Balance Sheet
A18: Rs. Crore | B18: FY2021 | C18: FY2022 | D18: FY2023 | E18: FY2024 | F18: FY2025
A19: Equity Share Capital | B19: 96 | C19: 96 | D19: 96 | E19: 96 | F19: 96
A20: Reserves & Surplus | B20: 12710 | C20: 13716 | D20: 15896 | E20: 18632 | F20: 19304
A21: Total Net Worth | B21: =B19+B20 -> 12806 | C21: =C19+C20 -> 13812 | D21: =D19+D20 -> 15992 | E21: =E19+E20 -> 18728 | F21: =F19+F20 -> 19400
A22: Borrowings | B22: 1093 | C22: 1587 | D22: 1933 | E22: 2474 | F22: 2290
A23: Other Liabilities | B23: 6456 | C23: 7560 | D23: 7854 | E23: 8698 | F23: 8665
A24: Total Liabilities & Equity | B24: =B21+B22+B23 -> 20355 | C24: =C21+C22+C23 -> 22959 | D24: =D21+D22+D23 -> 25779 | E24: =E21+E22+E23 -> 29900 | F24: =F21+F22+F23 -> 30355
A25: Fixed Assets (Net) + CWIP | B25: 6042 | C25: 5945 | D25: 6790 | E25: 9845 | F25: 10474
A26: Investments | B26: 4737 | C26: 3248 | D26: 4262 | E26: 4588 | F26: 4725
A27: Other Assets (incl. net working capital) | B27: 9576 | C27: 13765 | D27: 14727 | E27: 15468 | F27: 15156
A28: Total Assets (check) | B28: =B25+B26+B27 -> 20355 | C28: =C25+C26+C27 -> 22958 | D28: =D25+D26+D27 -> 25779 | E28: =E25+E26+E27 -> 29901 | F28: =F25+F26+F27 -> 30355
A30: Cash Flow
A31: Rs. Crore | B31: FY2021 | C31: FY2022 | D31: FY2023 | E31: FY2024 | F31: FY2025
A32: Cash from Operating Activity | B32: 3683 | C32: 986 | D32: 4193 | E32: 6104 | F32: 4424
A33: Free Cash Flow (reported) | B33: 3422 | C33: 475 | D33: 2774 | E33: 3613 | F33: 2604
A35: Shares Outstanding (Cr.) | F35: 97.03
A36: Market Price per Share (Jan 2026, Rs.) | F36: 2665
A37: Market Capitalization (Rs. Cr.) | F37: =F35*F36 -> 258584.95

Sheet Assumptions
A1: Forecast Assumptions (blue = editable input)
A3: Driver | B3: FY2026E | C3: FY2027E | D3: FY2028E | E3: FY2029E | F3: FY2030E
A4: Revenue growth % | B4: 0.02 | C4: 0.06 | D4: 0.07 | E4: 0.07 | F4: 0.07
A5: EBITDA margin % | B5: 0.18 | C5: 0.185 | D5: 0.19 | E5: 0.19 | F5: 0.19
A6: D&A (% of revenue) | B6: 0.028 | C6: 0.028 | D6: 0.028 | E6: 0.028 | F6: 0.028
A7: Capex (% of revenue) | B7: 0.04 | C7: 0.04 | D7: 0.038 | E7: 0.036 | F7: 0.035
A8: Incremental NWC (% of revenue change) | B8: 0.12 | C8: 0.12 | D8: 0.12 | E8: 0.12 | F8: 0.12
A9: Tax rate % | B9: 0.25 | C9: 0.25 | D9: 0.25 | E9: 0.25 | F9: 0.25
A12: WACC build-up (CAPM)
A13: Risk-free rate (10Y India G-Sec) | B13: 0.07
A14: Equity beta (assumption) | B14: 0.75
A15: Equity risk premium (India) | B15: 0.065
A16: Cost of equity (Ke) | B16: =B13+B14*B15 -> 0.11875
A17: Pre-tax cost of debt (Interest/avg borrowings) | B17: =Historicals!F10/((Historicals!E22+Historicals!F22)/2) -> 0.095298069
A18: Post-tax cost of debt (Kd) | B18: =B17*(1-B9) -> 0.071473552
A19: Equity value (FY25 net worth, Rs. Cr.) | B19: =Historicals!F21 -> 19400
A20: Debt value (FY25 borrowings, Rs. Cr.) | B20: =Historicals!F22 -> 2290
A21: Weight of equity | B21: =B19/(B19+B20) -> 0.89442139
A22: Weight of debt | B22: =B20/(B19+B20) -> 0.10557861
A23: WACC | B23: =B21*B16+B22*B18 -> 0.11375862
A25: Terminal growth rate (g) | B25: 0.05
A27: Note: beta and equity risk premium are analyst assumptions (Asian Paints does not publish a beta;
A28: 0.75 reflects its historically low volatility as a large-cap consumer staple).

Sheet Forecast
A1: 3-Statement Forecast, FY2026E-FY2030E (Rs. Crore)
A3: Rs. Crore | B3: FY2025A | C3: FY2026E | D3: FY2027E | E3: FY2028E | F3: FY2029E | G3: FY2030E
A4: Net Sales | B4: =Historicals!F5 -> 33906 | C4: =B4*(1+Assumptions!B4) -> 34584.12 | D4: =C4*(1+Assumptions!C4) -> 36659.167 | E4: =D4*(1+Assumptions!D4) -> 39225.309 | F4: =E4*(1+Assumptions!E4) -> 41971.081 | G4: =F4*(1+Assumptions!F4) -> 44909.056
A5: EBITDA | B5: =Historicals!F7 -> 6007 | C5: =C4*Assumptions!B5 -> 6225.1416 | D5: =D4*Assumptions!C5 -> 6781.9459 | E5: =E4*Assumptions!D5 -> 7452.8087 | F5: =F4*Assumptions!E5 -> 7974.5053 | G5: =G4*Assumptions!F5 -> 8532.7207
A6: EBITDA margin % | B6: =B5/B4 -> 0.17716628 | C6: =C5/C4 -> 0.18 | D6: =D5/D4 -> 0.185 | E6: =E5/E4 -> 0.19 | F6: =F5/F4 -> 0.19 | G6: =G5/G4 -> 0.19
A7: Less: D&A | B7: =Historicals!F11 -> 1026 | C7: =C4*Assumptions!B6 -> 968.35536 | D7: =D4*Assumptions!C6 -> 1026.4567 | E7: =E4*Assumptions!D6 -> 1098.3086 | F7: =F4*Assumptions!E6 -> 1175.1903 | G7: =G4*Assumptions!F6 -> 1257.4536
A8: EBIT | B8: =B5-B7 -> 4981 | C8: =C5-C7 -> 5256.7862 | D8: =D5-D7 -> 5755.4893 | E8: =E5-E7 -> 6354.5 | F8: =F5-F7 -> 6799.315 | G8: =G5-G7 -> 7275.2671
A9: Less: Tax on EBIT | C9: =C8*Assumptions!B9 -> 1314.1966 | D9: =D8*Assumptions!C9 -> 1438.8723 | E9: =E8*Assumptions!D9 -> 1588.625 | F9: =F8*Assumptions!E9 -> 1699.8288 | G9: =G8*Assumptions!F9 -> 1818.8168
A10: NOPAT (EBIT after tax) | C10: =C8-C9 -> 3942.5897 | D10: =D8-D9 -> 4316.6169 | E10: =E8-E9 -> 4765.875 | F10: =F8-F9 -> 5099.4863 | G10: =G8-G9 -> 5456.4503
A12: Free Cash Flow to Firm build-up
A13: NOPAT | C13: =C10 -> 3942.5897 | D13: =D10 -> 4316.6169 | E13: =E10 -> 4765.875 | F13: =F10 -> 5099.4863 | G13: =G10 -> 5456.4503
A14: Add: D&A | C14: =C7 -> 968.35536 | D14: =D7 -> 1026.4567 | E14: =E7 -> 1098.3086 | F14: =F7 -> 1175.1903 | G14: =G7 -> 1257.4536
A15: Less: Capex | C15: =C4*Assumptions!B7 -> 1383.3648 | D15: =D4*Assumptions!C7 -> 1466.3667 | E15: =E4*Assumptions!D7 -> 1490.5617 | F15: =F4*Assumptions!E7 -> 1510.9589 | G15: =G4*Assumptions!F7 -> 1571.817
A16: Less: Increase in Net Working Capital | C16: =(C4-B4)*Assumptions!B8 -> 81.3744 | D16: =(D4-C4)*Assumptions!C8 -> 249.00566 | E16: =(E4-D4)*Assumptions!D8 -> 307.937 | F16: =(F4-E4)*Assumptions!E8 -> 329.49259 | G16: =(G4-F4)*Assumptions!F8 -> 352.55708
A17: Free Cash Flow to Firm (FCFF) | C17: =C13+C14-C15-C16 -> 3446.2058 | D17: =D13+D14-D15-D16 -> 3627.7013 | E17: =E13+E14-E15-E16 -> 4065.6849 | F17: =F13+F14-F15-F16 -> 4434.225 | G17: =G13+G14-G15-G16 -> 4789.5299

Sheet DCF Valuation
A1: DCF Valuation - Asian Paints Ltd.
A3: Rs. Crore | B3: FY2026E | C3: FY2027E | D3: FY2028E | E3: FY2029E | F3: FY2030E
A4: Forecast year | B4: 1 | C4: 2 | D4: 3 | E4: 4 | F4: 5
A5: FCFF | B5: =Forecast!C17 -> 3446.2058 | C5: =Forecast!D17 -> 3627.7013 | D5: =Forecast!E17 -> 4065.6849 | E5: =Forecast!F17 -> 4434.225 | F5: =Forecast!G17 -> 4789.5299
A6: Discount factor @ WACC | B6: =1/(1+Assumptions!$B$23)^B4 -> 0.89786062 | C6: =1/(1+Assumptions!$B$23)^C4 -> 0.80615369 | D6: =1/(1+Assumptions!$B$23)^D4 -> 0.72381365 | E6: =1/(1+Assumptions!$B$23)^E4 -> 0.64988377 | F6: =1/(1+Assumptions!$B$23)^F4 -> 0.58350504
A7: PV of FCFF | B7: =B5*B6 -> 3094.2125 | C7: =C5*C6 -> 2924.4848 | D7: =D5*D6 -> 2942.7982 | E7: =E5*E6 -> 2881.7309 | F7: =F5*F6 -> 2794.7148
A9: Sum of PV of FCFF (FY26E-FY30E) | B9: =SUM(B7:F7) -> 14637.941
A11: Terminal Value (Gordon Growth Method)
A12: Terminal year FCFF (FY30E) | B12: =F5 -> 4789.5299
A13: Terminal growth rate (g) | B13: =Assumptions!B25 -> 0.05
A14: Terminal FCFF (FY31E) = FY30E x (1+g) | B14: =B12*(1+B13) -> 5029.0063
A15: Terminal Value @ end of FY30E = TermFCFF/(WACC-g) | B15: =B14/(Assumptions!B23-B13) -> 78875.711
A16: PV of Terminal Value | B16: =B15*F6 -> 46024.375
A18: Enterprise Value | B18: =B9+B16 -> 60662.316
A19: Less: Net Debt (FY25 Borrowings - Investments) | B19: =Historicals!F22-Historicals!F26 -> -2435
A20: Equity Value | B20: =B18-B19 -> 63097.316
A21: Shares Outstanding (Cr.) | B21: =Historicals!F35 -> 97.03
A22: DCF Value per Share (Rs.) | B22: =B20/B21 -> 650.28667
A24: Current Market Price (Jan 2026, Rs.) | B24: =Historicals!F36 -> 2665
A25: Upside / (Downside) to DCF Value | B25: =B22/B24-1 -> -0.75598999
A27: Note: Equity Value (Rs. Crore) / Shares Outstanding (Crore) gives value per share directly in Rupees,
A28: since both figures are expressed in the same Crore scale.

Sheet Sensitivity
A1: Sensitivity: Value per Share (Rs.) - WACC vs. Terminal Growth Rate
A2: Computed independently for each WACC/g pair using the same FCFF stream as the DCF Valuation tab.
A4: WACC \ Terminal g | B4: 0.03 | C4: 0.04 | D4: 0.05 | E4: 0.06 | F4: 0.07
A5: 0.093 | B5: =('DCF Valuation'!$B$5/(1+0.093)^1+'DCF Valuation'!$C$5/(1+0.093)^2+'DCF Valuation'!$D$5/(1+0.093)^3+'DCF Valuation'!$E$5/(1+0.093)^4+'DCF Valuation'!$F$5/(1+0.093)^5+('DCF Valuation'!$F$5*(1+B$4)/(0.093-B$4))/(1+0.093)^5-'DCF Valuation'!$B$19)/'DCF Valuation'!$B$21 -> 701.98803 | C5: =('DCF Valuation'!$B$5/(1+0.093)^1+'DCF Valuation'!$C$5/(1+0.093)^2+'DCF Valuation'!$D$5/(1+0.093)^3+'DCF Valuation'!$E$5/(1+0.093)^4+'DCF Valuation'!$F$5/(1+0.093)^5+('DCF Valuation'!$F$5*(1+C$4)/(0.093-C$4))/(1+0.093)^5-'DCF Valuation'!$B$19)/'DCF Valuation'!$B$21 -> 805.57134 | D5: =('DCF Valuation'!$B$5/(1+0.093)^1+'DCF Valuation'!$C$5/(1+0.093)^2+'DCF Valuation'!$D$5/(1+0.093)^3+'DCF Valuation'!$E$5/(1+0.093)^4+'DCF Valuation'!$F$5/(1+0.093)^5+('DCF Valuation'!$F$5*(1+D$4)/(0.093-D$4))/(1+0.093)^5-'DCF Valuation'!$B$19)/'DCF Valuation'!$B$21 -> 957.33293 | E5: =('DCF Valuation'!$B$5/(1+0.093)^1+'DCF Valuation'!$C$5/(1+0.093)^2+'DCF Valuation'!$D$5/(1+0.093)^3+'DCF Valuation'!$E$5/(1+0.093)^4+'DCF Valuation'!$F$5/(1+0.093)^5+('DCF Valuation'!$F$5*(1+E$4)/(0.093-E$4))/(1+0.093)^5-'DCF Valuation'!$B$19)/'DCF Valuation'!$B$21 -> 1201.0713 | F5: =('DCF Valuation'!$B$5/(1+0.093)^1+'DCF Valuation'!$C$5/(1+0.093)^2+'DCF Valuation'!$D$5/(1+0.093)^3+'DCF Valuation'!$E$5/(1+0.093)^4+'DCF Valuation'!$F$5/(1+0.093)^5+('DCF Valuation'!$F$5*(1+F$4)/(0.093-F$4))/(1+0.093)^5-'DCF Valuation'!$B$19)/'DCF Valuation'!$B$21 -> 1656.7559
A6: 0.103 | B6: =('DCF Valuation'!$B$5/(1+0.103)^1+'DCF Valuation'!$C$5/(1+0.103)^2+'DCF Valuation'!$D$5/(1+0.103)^3+'DCF Valuation'!$E$5/(1+0.103)^4+'DCF Valuation'!$F$5/(1+0.103)^5+('DCF Valuation'!$F$5*(1+B$4)/(0.103-B$4))/(1+0.103)^5-'DCF Valuation'!$B$19)/'DCF Valuation'!$B$21 -> 606.96426 | C6: =('DCF Valuation'!$B$5/(1+0.103)^1+'DCF Valuation'!$C$5/(1+0.103)^2+'DCF Valuation'!$D$5/(1+0.103)^3+'DCF Valuation'!$E$5/(1+0.103)^4+'DCF Valuation'!$F$5/(1+0.103)^5+('DCF Valuation'!$F$5*(1+C$4)/(0.103-C$4))/(1+0.103)^5-'DCF Valuation'!$B$19)/'DCF Valuation'!$B$21 -> 679.47818 | D6: =('DCF Valuation'!$B$5/(1+0.103)^1+'DCF Valuation'!$C$5/(1+0.103)^2+'DCF Valuation'!$D$5/(1+0.103)^3+'DCF Valuation'!$E$5/(1+0.103)^4+'DCF Valuation'!$F$5/(1+0.103)^5+('DCF Valuation'!$F$5*(1+D$4)/(0.103-D$4))/(1+0.103)^5-'DCF Valuation'!$B$19)/'DCF Valuation'!$B$21 -> 779.35585 | E6: =('DCF Valuation'!$B$5/(1+0.103)^1+'DCF Valuation'!$C$5/(1+0.103)^2+'DCF Valuation'!$D$5/(1+0.103)^3+'DCF Valuation'!$E$5/(1+0.103)^4+'DCF Valuation'!$F$5/(1+0.103)^5+('DCF Valuation'!$F$5*(1+E$4)/(0.103-E$4))/(1+0.103)^5-'DCF Valuation'!$B$19)/'DCF Valuation'!$B$21 -> 925.68824 | F6: =('DCF Valuation'!$B$5/(1+0.103)^1+'DCF Valuation'!$C$5/(1+0.103)^2+'DCF Valuation'!$D$5/(1+0.103)^3+'DCF Valuation'!$E$5/(1+0.103)^4+'DCF Valuation'!$F$5/(1+0.103)^5+('DCF Valuation'!$F$5*(1+F$4)/(0.103-F$4))/(1+0.103)^5-'DCF Valuation'!$B$19)/'DCF Valuation'!$B$21 -> 1160.7069
A7: 0.113 | B7: =('DCF Valuation'!$B$5/(1+0.113)^1+'DCF Valuation'!$C$5/(1+0.113)^2+'DCF Valuation'!$D$5/(1+0.113)^3+'DCF Valuation'!$E$5/(1+0.113)^4+'DCF Valuation'!$F$5/(1+0.113)^5+('DCF Valuation'!$F$5*(1+B$4)/(0.113-B$4))/(1+0.113)^5-'DCF Valuation'!$B$19)/'DCF Valuation'!$B$21 -> 534.90897 | C7: =('DCF Valuation'!$B$5/(1+0.113)^1+'DCF Valuation'!$C$5/(1+0.113)^2+'DCF Valuation'!$D$5/(1+0.113)^3+'DCF Valuation'!$E$5/(1+0.113)^4+'DCF Valuation'!$F$5/(1+0.113)^5+('DCF Valuation'!$F$5*(1+C$4)/(0.113-C$4))/(1+0.113)^5-'DCF Valuation'!$B$19)/'DCF Valuation'!$B$21 -> 587.99806 | D7: =('DCF Valuation'!$B$5/(1+0.113)^1+'DCF Valuation'!$C$5/(1+0.113)^2+'DCF Valuation'!$D$5/(1+0.113)^3+'DCF Valuation'!$E$5/(1+0.113)^4+'DCF Valuation'!$F$5/(1+0.113)^5+('DCF Valuation'!$F$5*(1+D$4)/(0.113-D$4))/(1+0.113)^5-'DCF Valuation'!$B$19)/'DCF Valuation'!$B$21 -> 657.94082 | E7: =('DCF Valuation'!$B$5/(1+0.113)^1+'DCF Valuation'!$C$5/(1+0.113)^2+'DCF Valuation'!$D$5/(1+0.113)^3+'DCF Valuation'!$E$5/(1+0.113)^4+'DCF Valuation'!$F$5/(1+0.113)^5+('DCF Valuation'!$F$5*(1+E$4)/(0.113-E$4))/(1+0.113)^5-'DCF Valuation'!$B$19)/'DCF Valuation'!$B$21 -> 754.27708 | F7: =('DCF Valuation'!$B$5/(1+0.113)^1+'DCF Valuation'!$C$5/(1+0.113)^2+'DCF Valuation'!$D$5/(1+0.113)^3+'DCF Valuation'!$E$5/(1+0.113)^4+'DCF Valuation'!$F$5/(1+0.113)^5+('DCF Valuation'!$F$5*(1+F$4)/(0.113-F$4))/(1+0.113)^5-'DCF Valuation'!$B$19)/'DCF Valuation'!$B$21 -> 895.4209
A8: 0.123 | B8: =('DCF Valuation'!$B$5/(1+0.123)^1+'DCF Valuation'!$C$5/(1+0.123)^2+'DCF Valuation'!$D$5/(1+0.123)^3+'DCF Valuation'!$E$5/(1+0.123)^4+'DCF Valuation'!$F$5/(1+0.123)^5+('DCF Valuation'!$F$5*(1+B$4)/(0.123-B$4))/(1+0.123)^5-'DCF Valuation'!$B$19)/'DCF Valuation'!$B$21 -> 478.41009 | C8: =('DCF Valuation'!$B$5/(1+0.123)^1+'DCF Valuation'!$C$5/(1+0.123)^2+'DCF Valuation'!$D$5/(1+0.123)^3+'DCF Valuation'!$E$5/(1+0.123)^4+'DCF Valuation'!$F$5/(1+0.123)^5+('DCF Valuation'!$F$5*(1+C$4)/(0.123-C$4))/(1+0.123)^5-'DCF Valuation'!$B$19)/'DCF Valuation'!$B$21 -> 518.61756 | D8: =('DCF Valuation'!$B$5/(1+0.123)^1+'DCF Valuation'!$C$5/(1+0.123)^2+'DCF Valuation'!$D$5/(1+0.123)^3+'DCF Valuation'!$E$5/(1+0.123)^4+'DCF Valuation'!$F$5/(1+0.123)^5+('DCF Valuation'!$F$5*(1+D$4)/(0.123-D$4))/(1+0.123)^5-'DCF Valuation'!$B$19)/'DCF Valuation'!$B$21 -> 569.84078 | E8: =('DCF Valuation'!$B$5/(1+0.123)^1+'DCF Valuation'!$C$5/(1+0.123)^2+'DCF Valuation'!$D$5/(1+0.123)^3+'DCF Valuation'!$E$5/(1+0.123)^4+'DCF Valuation'!$F$5/(1+0.123)^5+('DCF Valuation'!$F$5*(1+E$4)/(0.123-E$4))/(1+0.123)^5-'DCF Valuation'!$B$19)/'DCF Valuation'!$B$21 -> 637.32534 | F8: =('DCF Valuation'!$B$5/(1+0.123)^1+'DCF Valuation'!$C$5/(1+0.123)^2+'DCF Valuation'!$D$5/(1+0.123)^3+'DCF Valuation'!$E$5/(1+0.123)^4+'DCF Valuation'!$F$5/(1+0.123)^5+('DCF Valuation'!$F$5*(1+F$4)/(0.123-F$4))/(1+0.123)^5-'DCF Valuation'!$B$19)/'DCF Valuation'!$B$21 -> 730.27577
A9: 0.133 | B9: =('DCF Valuation'!$B$5/(1+0.133)^1+'DCF Valuation'!$C$5/(1+0.133)^2+'DCF Valuation'!$D$5/(1+0.133)^3+'DCF Valuation'!$E$5/(1+0.133)^4+'DCF Valuation'!$F$5/(1+0.133)^5+('DCF Valuation'!$F$5*(1+B$4)/(0.133-B$4))/(1+0.133)^5-'DCF Valuation'!$B$19)/'DCF Valuation'!$B$21 -> 432.93416 | C9: =('DCF Valuation'!$B$5/(1+0.133)^1+'DCF Valuation'!$C$5/(1+0.133)^2+'DCF Valuation'!$D$5/(1+0.133)^3+'DCF Valuation'!$E$5/(1+0.133)^4+'DCF Valuation'!$F$5/(1+0.133)^5+('DCF Valuation'!$F$5*(1+C$4)/(0.133-C$4))/(1+0.133)^5-'DCF Valuation'!$B$19)/'DCF Valuation'!$B$21 -> 464.20554 | D9: =('DCF Valuation'!$B$5/(1+0.133)^1+'DCF Valuation'!$C$5/(1+0.133)^2+'DCF Valuation'!$D$5/(1+0.133)^3+'DCF Valuation'!$E$5/(1+0.133)^4+'DCF Valuation'!$F$5/(1+0.133)^5+('DCF Valuation'!$F$5*(1+D$4)/(0.133-D$4))/(1+0.133)^5-'DCF Valuation'!$B$19)/'DCF Valuation'!$B$21 -> 503.01219 | E9: =('DCF Valuation'!$B$5/(1+0.133)^1+'DCF Valuation'!$C$5/(1+0.133)^2+'DCF Valuation'!$D$5/(1+0.133)^3+'DCF Valuation'!$E$5/(1+0.133)^4+'DCF Valuation'!$F$5/(1+0.133)^5+('DCF Valuation'!$F$5*(1+E$4)/(0.133-E$4))/(1+0.133)^5-'DCF Valuation'!$B$19)/'DCF Valuation'!$B$21 -> 552.4508 | F9: =('DCF Valuation'!$B$5/(1+0.133)^1+'DCF Valuation'!$C$5/(1+0.133)^2+'DCF Valuation'!$D$5/(1+0.133)^3+'DCF Valuation'!$E$5/(1+0.133)^4+'DCF Valuation'!$F$5/(1+0.133)^5+('DCF Valuation'!$F$5*(1+F$4)/(0.133-F$4))/(1+0.133)^5-'DCF Valuation'!$B$19)/'DCF Valuation'!$B$21 -> 617.58421
A11: Base case (WACC ~11.3%, g = 5.0%) highlighted in yellow - matches the DCF Valuation tab output.

Sheet Comps
A1: Comparable Company Analysis - Indian Decorative Paints Sector
A2: Source: Screener.in company pages, data as of Q4 FY26 / TTM (approx. May-Jun 2026)
A4: Company | B4: Mkt Cap (Rs. Cr.) | C4: TTM Revenue (Rs. Cr.) | D4: TTM Net Profit (Rs. Cr.) | E4: P/E (x) | F4: P/Sales (x)
A5: Asian Paints Ltd | B5: 254389 | C5: 34696 | D5: 3910 | E5: =B5/D5 -> 65.061125 | F5: =B5/C5 -> 7.3319403
A6: Berger Paints India Ltd | B6: 57979 | C6: 11880 | D6: 1128 | E6: =B6/D6 -> 51.399823 | F6: =B6/C6 -> 4.8803872
A7: Kansai Nerolac Paints Ltd | B7: 16461 | C7: 8052 | D7: 576 | E7: =B7/D7 -> 28.578125 | F7: =B7/C7 -> 2.0443368
A9: Peer average (excl. Asian Paints) | E9: =AVERAGE(E6:E7) -> 39.988974 | F9: =AVERAGE(F6:F7) -> 3.462362
A12: Implied Valuation of Asian Paints at Peer Average Multiples
A13: Method | B13: Asian Paints FY25 metric | C13: Peer avg. multiple | D13: Implied Equity Value (Rs. Cr.) | E13: Implied Value / Share (Rs.)
A14: P/E method | B14: =Historicals!F14 -> 3725.92 | C14: =E9 -> 39.988974 | D14: =B14*C14 -> 148995.72 | E14: =D14/Historicals!F35 -> 1535.5634
A15: P/Sales method | B15: =Historicals!F5 -> 33906 | C15: =F9 -> 3.462362 | D15: =B15*C15 -> 117394.85 | E15: =D15/Historicals!F35 -> 1209.882
A17: Comps-implied value range (Rs./share) | B17: =MIN(E14:E15) -> 1209.882 | C17: to | D17: =MAX(E14:E15) -> 1535.5634
A19: Note: Asian Paints trades at a structural premium to peers (leadership scale, brand, distribution reach),
A20: so comps-implied values here are a sanity check on the DCF, not a standalone target.

Sheet Summary
A1: Valuation Summary & Recommendation - Asian Paints Ltd.
A3: Metric | B3: Value
A4: Current Market Price (Jan 2026) | B4: ='DCF Valuation'!B24 -> 2665
A5: DCF Value per Share | B5: ='DCF Valuation'!B22 -> 650.28667
A6: DCF Upside / (Downside) | B6: ='DCF Valuation'!B25 -> -0.75598999
A7: Comps-Implied Value (low) | B7: =Comps!B17 -> 1209.882
A8: Comps-Implied Value (high) | B8: =Comps!D17 -> 1535.5634
A9: WACC used | B9: =Assumptions!B23 -> 0.11375862
A10: Terminal growth rate used | B10: =Assumptions!B25 -> 0.05
A12: INVESTMENT VIEW
A13: The base-case DCF (2-7% revenue growth, 18-19% EBITDA margin, ~11.3% WACC) implies a fair value of roughly
A14: Rs. 650/share - a P/E of ~17x FY25 earnings. The January 2026 market price of Rs. 2,665 implies ~70x FY25
A15: earnings, well above both the DCF and the peer average P/E of ~34x (Comps tab).
A17: The gap is consistent with Asian Paints' long-standing 'quality compounder' premium: the market is pricing in
A18: durability, brand moat and reinvestment runway well beyond what a conservative 5-year explicit forecast plus
A19: Gordon Growth terminal value can capture. That premium has persisted for years and is not, by itself, evidence
A20: the stock is mispriced - but it does mean this DCF offers little margin of safety at the current price, and
A21: returns from here depend more on multiple sustainability than on this model's fundamental cash flows.
A23: View: HOLD - fundamentally sound business, but the current price already assumes a best-case competitive
A24: outcome (successful defense of share against Birla Opus) that this base case does not build in. This is a
A25: model output for a learning project, not investment advice.
